scryfall/__init__.py
scryfall/const.py
scryfall/utils.py
scryfall/client/__init__.py
scryfall/client/error.py
scryfall/client/route.py
scryfall/client/http/http_requests/card.py
scryfall/client/http/http_requests/set.py
scryfall/models/__init__.py
scryfall/models/api.py
scryfall/models/base.py
scryfall/models/bulk.py
scryfall/models/cards.py
scryfall/models/catalogs.py
scryfall/models/enums.py
scryfall/models/rulings.py
scryfall/models/sets.py
scryfall/models/symbols.py
scryfall/models/internal/protocols.py
scryfall_py-0.1.1.dist-info/METADATA
scryfall_py-0.1.1.dist-info/WHEEL
scryfall_py-0.1.1.dist-info/RECORD
